pyTSPA/__init__.py
pyTSPA/data.py
pyTSPA/metrics.py
pyTSPA/visualization.py
pytspa_toolbox-0.1.1.dist-info/licenses/LICENSE
pytspa_toolbox-0.1.1.dist-info/METADATA
pytspa_toolbox-0.1.1.dist-info/WHEEL
pytspa_toolbox-0.1.1.dist-info/top_level.txt
pytspa_toolbox-0.1.1.dist-info/RECORD
